gitfighters/__init__.py
gitfighters/git_fighters.py
gitfighters/latex.py
gitfighters/parsing.py
gitfighters/vector.py
gitfighters/visualize.py
gitfighters-1.1.0.data/scripts/cli.py
tests/__init__.py
tests/test_AD.py
tests/test_cli.py
tests/test_fightingAD.py
tests/test_latex.py
tests/test_parsing.py
tests/test_visualize.py
gitfighters-1.1.0.dist-info/LICENSE
gitfighters-1.1.0.dist-info/METADATA
gitfighters-1.1.0.dist-info/WHEEL
gitfighters-1.1.0.dist-info/top_level.txt
gitfighters-1.1.0.dist-info/RECORD
