Metadata-Version: 2.1
Name: gitfighters
Version: 1.1.0
Summary: Automatic Differentiation Library
Home-page: https://github.com/Git-fighters/cs107-FinalProject
Author: cs107-project-group10
Author-email: hugo_montenegro@g.harvard.edu, talelokvenec@g.harvard.edu, mananahakobyan@g.harvard.edu, Feige@g.harvard.edu
License: UNKNOWN
Platform: UNKNOWN
Classifier: Programming Language :: Python :: 3
Classifier: License :: OSI Approved :: MIT License
Classifier: Operating System :: OS Independent
Requires-Dist: matplotlib
Requires-Dist: nltk
Requires-Dist: numpy
